ehelply_python_sdk/__init__.py
ehelply_python_sdk/api_client.py
ehelply_python_sdk/configuration.py
ehelply_python_sdk/exceptions.py
ehelply_python_sdk/rest.py
ehelply_python_sdk/schemas.py
ehelply_python_sdk/api/__init__.py
ehelply_python_sdk/api/billing_api.py
ehelply_python_sdk/api/category_api.py
ehelply_python_sdk/api/companies_api.py
ehelply_python_sdk/api/default_api.py
ehelply_python_sdk/api/logging_api.py
ehelply_python_sdk/api/meta_api.py
ehelply_python_sdk/api/monitor_api.py
ehelply_python_sdk/api/notes_api.py
ehelply_python_sdk/api/places_api.py
ehelply_python_sdk/api/projects_api.py
ehelply_python_sdk/api/security_api.py
ehelply_python_sdk/api/staff_api.py
ehelply_python_sdk/api/support_api.py
ehelply_python_sdk/api/tag_api.py
ehelply_python_sdk/api/users_api.py
ehelply_python_sdk/api/billing_api_endpoints/__init__.py
ehelply_python_sdk/api/billing_api_endpoints/create_billing_account.py
ehelply_python_sdk/api/billing_api_endpoints/get_client_secret.py
ehelply_python_sdk/api/billing_api_endpoints/has_payment.py
ehelply_python_sdk/api/billing_api_endpoints/list_payment_methods.py
ehelply_python_sdk/api/billing_api_endpoints/process_payment.py
ehelply_python_sdk/api/billing_api_endpoints/reconcile_payment_method.py
ehelply_python_sdk/api/billing_api_endpoints/remove_payment_method.py
ehelply_python_sdk/api/category_api_endpoints/__init__.py
ehelply_python_sdk/api/category_api_endpoints/create_category_places_categories_post.py
ehelply_python_sdk/api/category_api_endpoints/delete_category_places_categories_category_uuid_delete.py
ehelply_python_sdk/api/category_api_endpoints/get_category_places_categories_category_uuid_get.py
ehelply_python_sdk/api/category_api_endpoints/search_categories_places_categories_get.py
ehelply_python_sdk/api/category_api_endpoints/update_category_places_categories_category_uuid_put.py
ehelply_python_sdk/api/companies_api_endpoints/__init__.py
ehelply_python_sdk/api/companies_api_endpoints/create_company_places_companies_post.py
ehelply_python_sdk-1.1.88.dist-info/METADATA
ehelply_python_sdk-1.1.88.dist-info/WHEEL
ehelply_python_sdk-1.1.88.dist-info/top_level.txt
ehelply_python_sdk-1.1.88.dist-info/RECORD
