Metadata-Version: 2.1
Name: ehelply-python-sdk
Version: 1.1.88
Summary: eHelply SDK - 1.1.88
Home-page: UNKNOWN
Author: Support
Author-email: support@ehelply.com
License: Apache 2.0
Keywords: OpenAPI,OpenAPI-Generator,eHelply SDK - 1.1.88
Platform: UNKNOWN
Requires-Python: >=3.9
Requires-Dist: urllib3 (>=1.15)
Requires-Dist: certifi
Requires-Dist: python-dateutil
Requires-Dist: frozendict (>=2.0.3)
